examples/OPC/rtl/opc_parameters.vh
/******************************************************************************
* Project : Open Peripheral Controller (OPC)
* File    : opc_parameters.vh
* Author  : Dr. Lukram Dhanachandra Singh
*
* Description:
* Global design parameters used throughout the OPC project.
******************************************************************************/

`ifndef OPC_PARAMETERS_VH
`define OPC_PARAMETERS_VH

//==============================================================
// Global Parameters
//==============================================================

parameter DATA_WIDTH = 32;
parameter ADDR_WIDTH = 8;
parameter GPIO_WIDTH = 8;
parameter NUM_REGISTERS = 8;

//----------------------------------------------------------------------
// APB Parameters
//----------------------------------------------------------------------

parameter APB_ADDR_WIDTH = 32;
parameter REG_ADDR_LSB   = 2;


//==============================================================
// Future Expansion
//==============================================================

parameter TIMER_WIDTH = 32;
parameter UART_DATA_WIDTH = 8;
parameter SPI_DATA_WIDTH = 8;
parameter I2C_DATA_WIDTH = 8;

`endif

examples/OPC/rtl/apb_wrapper.v
`timescale 1ns / 1ps
//////////////////////////////////////////////////////////////////////////////////
// Project : Open Peripheral Controller (OPC)
// Module  : APB Wrapper
// File    : apb_wrapper.v
//
// Description:
// ------------
// Generic APB3 slave wrapper for the Open Peripheral Controller.
// Converts APB transactions into the generic register interface
// used by the existing OPC.
//
// Author  :Dr. Lukram Dhanachandra Singh
// Version : 1.0
//////////////////////////////////////////////////////////////////////////////////

`include "opc_parameters.vh"

module apb_wrapper
(
    //----------------------------------------------------------------------
    // Clock and Reset
    //----------------------------------------------------------------------

    input  wire                     PCLK,
    input  wire                     PRESETn,

    //----------------------------------------------------------------------
    // APB Slave Interface
    //----------------------------------------------------------------------

    input  wire                     PSEL,
    input  wire                     PENABLE,
    input  wire                     PWRITE,

    //input  wire [31:0]              PADDR,
    input wire [APB_ADDR_WIDTH-1:0] PADDR,
    input  wire [DATA_WIDTH-1:0]    PWDATA,

    output reg  [DATA_WIDTH-1:0]    PRDATA,
    output reg                      PREADY,
    output reg                      PSLVERR,

    //----------------------------------------------------------------------
    // Generic Register Interface
    //----------------------------------------------------------------------

    output reg                      write_en_o,
    output reg                      read_en_o,

    output reg [ADDR_WIDTH-1:0]     addr_o,
    output reg [DATA_WIDTH-1:0]     wdata_o,

    input wire [DATA_WIDTH-1:0]     rdata_i
);

///////////////////////////////////////////////////////////////////////////////
// Internal Signals
///////////////////////////////////////////////////////////////////////////////

//wire apb_setup_w;
wire apb_access_w;

wire apb_write_access_w;
wire apb_read_access_w;


///////////////////////////////////////////////////////////////////////////////
// Address Decode
///////////////////////////////////////////////////////////////////////////////

wire [ADDR_WIDTH-1:0] reg_addr_w;
wire                  valid_addr_w;

assign reg_addr_w = PADDR[REG_ADDR_LSB + ADDR_WIDTH - 1 :
                          REG_ADDR_LSB];

assign valid_addr_w = (reg_addr_w < NUM_REGISTERS);
///////////////////////////////////////////////////////////////////////////////
// APB Transaction Detection
///////////////////////////////////////////////////////////////////////////////

//assign apb_setup_w  = PSEL & (~PENABLE);

assign apb_access_w = PSEL & PENABLE;

assign apb_write_access_w = apb_access_w & PWRITE;

assign apb_read_access_w  = apb_access_w & (~PWRITE);

///////////////////////////////////////////////////////////////////////////////
// APB Sequential Logic
///////////////////////////////////////////////////////////////////////////////

always @(posedge PCLK or negedge PRESETn)
begin

    //----------------------------------------------------------------------
    // Reset
    //----------------------------------------------------------------------

    if(!PRESETn)
    begin

        write_en_o <= 1'b0;
        read_en_o  <= 1'b0;

        addr_o     <= {ADDR_WIDTH{1'b0}};
        wdata_o    <= {DATA_WIDTH{1'b0}};

        PRDATA     <= {DATA_WIDTH{1'b0}};

        PREADY     <= 1'b0;
        PSLVERR    <= 1'b0;

    end

        else
    begin

        //----------------------------------------------------------
        // Default Outputs
        //----------------------------------------------------------

        write_en_o <= 1'b0;
        read_en_o  <= 1'b0;

        PREADY     <= 1'b0;
        PSLVERR    <= 1'b0;

	        //----------------------------------------------------------
        // APB Write
        //----------------------------------------------------------

        if(apb_write_access_w)
	begin
	    PREADY <= 1'b1;

	    if(valid_addr_w)
	    begin
	        write_en_o <= 1'b1;
	        addr_o <= PADDR[ADDR_WIDTH-1:0];
		//addr_o     <= reg_addr_w;
 	        wdata_o    <= PWDATA;
	        PSLVERR    <= 1'b0;
	    end
	    else
	    begin
	        write_en_o <= 1'b0;
	        PSLVERR    <= 1'b1;
	    end
	end
        //----------------------------------------------------------
        // APB Read
        //----------------------------------------------------------

        else if(apb_read_access_w)
	begin
	    PREADY <= 1'b1;

	    if(valid_addr_w)
	    begin
	        read_en_o <= 1'b1;
	        addr_o <= PADDR[ADDR_WIDTH-1:0];
		//addr_o    <= reg_addr_w;
	        PRDATA    <= rdata_i;
	        PSLVERR   <= 1'b0;
	    end
	    else
	    begin
	        read_en_o <= 1'b0;
	        PRDATA    <= {DATA_WIDTH{1'b0}};
	        PSLVERR   <= 1'b1;
	    end
	end

    end

end

endmodule

examples/OPC/tb/apb_wrapper_tb.v
`timescale 1ns / 1ps

//////////////////////////////////////////////////////////////////////////////////
// Project : Open Peripheral Controller (OPC)
// Module  : APB Wrapper Testbench
// File    : apb_wrapper_tb.v
//
// Description:
// ------------
// Self-checking testbench for APB Wrapper.
//
//////////////////////////////////////////////////////////////////////////////////

`include "../rtl/opc_parameters.vh"

module apb_wrapper_tb;

    //----------------------------------------------------------------------
    // Clock and Reset
    //----------------------------------------------------------------------

    reg PCLK;
    reg PRESETn;

    //----------------------------------------------------------------------
    // APB Master Signals
    //----------------------------------------------------------------------

    reg                     PSEL;
    reg                     PENABLE;
    reg                     PWRITE;

    reg [APB_ADDR_WIDTH-1:0] PADDR;
    reg [DATA_WIDTH-1:0]     PWDATA;

    wire [DATA_WIDTH-1:0]    PRDATA;
    wire                     PREADY;
    wire                     PSLVERR;

    //----------------------------------------------------------------------
    // Generic Register Interface
    //----------------------------------------------------------------------

    wire                     write_en_o;
    wire                     read_en_o;

    wire [ADDR_WIDTH-1:0]    addr_o;
    wire [DATA_WIDTH-1:0]    wdata_o;

    reg  [DATA_WIDTH-1:0]    rdata_i;

///////////////////////////////////////////////////////////////////////
// Test Statistics
///////////////////////////////////////////////////////////////////////

	integer pass_count;
	integer fail_count;

    //----------------------------------------------------------------------
    // DUT
    //----------------------------------------------------------------------

    apb_wrapper dut
    (
        .PCLK(PCLK),
        .PRESETn(PRESETn),

        .PSEL(PSEL),
        .PENABLE(PENABLE),
        .PWRITE(PWRITE),

        .PADDR(PADDR),
        .PWDATA(PWDATA),

        .PRDATA(PRDATA),
        .PREADY(PREADY),
        .PSLVERR(PSLVERR),

        .write_en_o(write_en_o),
        .read_en_o(read_en_o),

        .addr_o(addr_o),
        .wdata_o(wdata_o),

        .rdata_i(rdata_i)
    );

    //----------------------------------------------------------------------
    // Clock Generation
    //----------------------------------------------------------------------

    initial
    begin
        PCLK = 0;

        forever #5 PCLK = ~PCLK;
    end

    //----------------------------------------------------------------------
    // Reset
    //----------------------------------------------------------------------

    task reset_dut;

    begin

        PRESETn = 0;

        PSEL    = 0;
        PENABLE = 0;
        PWRITE  = 0;

        PADDR   = 0;
        PWDATA  = 0;

        rdata_i = 0;

        repeat(5) @(posedge PCLK);

        PRESETn = 1;

        repeat(2) @(posedge PCLK);

    end

    endtask

    //----------------------------------------------------------------------
    // APB WRITE
    //----------------------------------------------------------------------

    task apb_write;

        input [APB_ADDR_WIDTH-1:0] address;
        input [DATA_WIDTH-1:0] data;

    begin

        @(posedge PCLK);

	PSEL    = 1;
	PENABLE = 0;
	PWRITE  = 1;

	PADDR   = address;
	PWDATA  = data;

        @(posedge PCLK);

        PENABLE = 1;

        @(posedge PCLK);

        PSEL    = 0;
        PENABLE = 0;
        PWRITE  = 0;

    end

    endtask

    //----------------------------------------------------------------------
    // APB READ
    //----------------------------------------------------------------------

    task apb_read;

        input [APB_ADDR_WIDTH-1:0] address;

    begin

        @(posedge PCLK);

        PSEL    = 1;
        PENABLE = 0;
        PWRITE  = 0;

        PADDR   = address;

        @(posedge PCLK);

        PENABLE = 1;

        @(posedge PCLK);

        PSEL    = 0;
        PENABLE = 0;

    end

    endtask

    //----------------------------------------------------------------------
    // Test Sequence
    //----------------------------------------------------------------------

    initial
    begin

        $dumpfile("apb_wrapper.vcd");
        $dumpvars(0, apb_wrapper_tb);

        reset_dut();
	pass_count = 0;
	fail_count = 0;

        //----------------------------------------------------------
        // Test Write
        //----------------------------------------------------------

        $display("------------------------------------------------");
        $display("APB WRITE TEST");
        $display("------------------------------------------------");

        apb_write(32'h00000004,32'h12345678);

        if(write_en_o)
	begin
	    $display("PASS : Write Enable Generated");
	    pass_count = pass_count + 1;
	end
	else
	begin
	    $display("FAIL : Write Enable NOT Generated");
	    fail_count = fail_count + 1;
	end

        //----------------------------------------------------------
        // Test Read
        //----------------------------------------------------------

        rdata_i = 32'hA5A55A5A;

        apb_read(32'h00000004);

        if(read_en_o)
	begin
	    $display("PASS : Read Enable Generated");
	    pass_count = pass_count + 1;
	end
	else
	begin
	    $display("FAIL : Read Enable NOT Generated");
	    fail_count = fail_count + 1;
	end

        if(PRDATA == 32'hA5A55A5A)
	begin
	    $display("PASS : Read Data Correct");
	    pass_count = pass_count + 1;
	end
	else
	begin
	    $display("FAIL : Read Data Incorrect");
	    fail_count = fail_count + 1;
	end

        repeat(10) @(posedge PCLK);

        $display("");
	$display("==============================================");
	$display("      APB Wrapper Verification Summary");
	$display("==============================================");

	$display("Passed Checks : %0d", pass_count);
	$display("Failed Checks : %0d", fail_count);

	if(fail_count == 0)
	    $display("OVERALL RESULT : PASS");
	else
	    $display("OVERALL RESULT : FAIL");

	$display("==============================================");

        $finish;

    end

endmodule

examples/OPC/apb_wrapper.vcd
$version Generated by VerilatedVcd $end
$timescale 1ps $end
 $scope module $unit $end
  $var wire 32 9 DATA_WIDTH [31:0] $end
  $var wire 32 : ADDR_WIDTH [31:0] $end
  $var wire 32 : GPIO_WIDTH [31:0] $end
  $var wire 32 : NUM_REGISTERS [31:0] $end
  $var wire 32 9 APB_ADDR_WIDTH [31:0] $end
  $var wire 32 ; REG_ADDR_LSB [31:0] $end
  $var wire 32 9 TIMER_WIDTH [31:0] $end
  $var wire 32 : UART_DATA_WIDTH [31:0] $end
  $var wire 32 : SPI_DATA_WIDTH [31:0] $end
  $var wire 32 : I2C_DATA_WIDTH [31:0] $end
 $upscope $end
 $scope module apb_wrapper_tb $end
  $var wire 1 5 PCLK $end
  $var wire 1 # PRESETn $end
  $var wire 1 $ PSEL $end
  $var wire 1 % PENABLE $end
  $var wire 1 & PWRITE $end
  $var wire 32 ' PADDR [31:0] $end
  $var wire 32 ( PWDATA [31:0] $end
  $var wire 32 . PRDATA [31:0] $end
  $var wire 1 / PREADY $end
  $var wire 1 0 PSLVERR $end
  $var wire 1 1 write_en_o $end
  $var wire 1 2 read_en_o $end
  $var wire 8 3 addr_o [7:0] $end
  $var wire 32 4 wdata_o [31:0] $end
  $var wire 32 ) rdata_i [31:0] $end
  $var wire 32 * pass_count [31:0] $end
  $var wire 32 + fail_count [31:0] $end
  $scope module dut $end
   $var wire 1 5 PCLK $end
   $var wire 1 # PRESETn $end
   $var wire 1 $ PSEL $end
   $var wire 1 % PENABLE $end
   $var wire 1 & PWRITE $end
   $var wire 32 ' PADDR [31:0] $end
   $var wire 32 ( PWDATA [31:0] $end
   $var wire 32 . PRDATA [31:0] $end
   $var wire 1 / PREADY $end
   $var wire 1 0 PSLVERR $end
   $var wire 1 1 write_en_o $end
   $var wire 1 2 read_en_o $end
   $var wire 8 3 addr_o [7:0] $end
   $var wire 32 4 wdata_o [31:0] $end
   $var wire 32 ) rdata_i [31:0] $end
   $var wire 1 6 apb_access_w $end
   $var wire 1 7 apb_write_access_w $end
   $var wire 1 8 apb_read_access_w $end
   $var wire 8 , reg_addr_w [7:0] $end
   $var wire 1 - valid_addr_w $end
  $upscope $end
 $upscope $end
$enddefinitions $end


#0
0#
0$
0%
0&
b00000000000000000000000000000000 '
b00000000000000000000000000000000 (
b00000000000000000000000000000000 )
b00000000000000000000000000000000 *
b00000000000000000000000000000000 +
b00000000 ,
1-
b00000000000000000000000000000000 .
0/
00
01
02
b00000000 3
b00000000000000000000000000000000 4
05
06
07
08
b00000000000000000000000000100000 9
b00000000000000000000000000001000 :
b00000000000000000000000000000010 ;
#5000
15
#10000
05
#15000
15
#20000
05
#25000
15
#30000
05
#35000
15
#40000
05
#45000
1#
15
#50000
05
#55000
15
#60000
05
#65000
15
#70000
05
#75000
1$
1&
b00000000000000000000000000000100 '
b00010010001101000101011001111000 (
b00000001 ,
15
#80000
05
#85000
1%
1/
11
b00000100 3
b00010010001101000101011001111000 4
15
16
17
#90000
05
#95000
0$
0%
0&
b10100101101001010101101001011010 )
b00000000000000000000000000000001 *
0/
01
15
06
07
#100000
05
#105000
1$
15
#110000
05
#115000
1%
b10100101101001010101101001011010 .
1/
12
15
16
18
#120000
05
#125000
0$
0%
b00000000000000000000000000000011 *
0/
02
15
06
08
