examples/OPC/rtl/opc_defines.vh
/******************************************************************************
* Project : Open Peripheral Controller (OPC)
* File    : opc_defines.vh
*
* Description:
* Register address definitions.
******************************************************************************/

`ifndef OPC_DEFINES_VH
`define OPC_DEFINES_VH

//==============================================================
// GPIO Register Addresses
//==============================================================

`define GPIO_DATA_ADDR      8'h00
`define GPIO_DIR_ADDR       8'h04
`define GPIO_IN_ADDR        8'h08
`define GPIO_OUT_ADDR       8'h0C

/**********************************************************************
* Register File Indices
**********************************************************************/

`define GPIO_DATA_REG      0
`define GPIO_DIR_REG       1

`define TIMER_CTRL_REG     2
`define TIMER_VALUE_REG    3

`define UART_CTRL_REG      4
`define UART_STATUS_REG    5

`define SPI_CTRL_REG       6
`define SPI_STATUS_REG     7

//==============================================================
// Future Peripheral Registers
//==============================================================

`define TIMER_CTRL_ADDR     8'h10
`define TIMER_COUNT_ADDR    8'h14

`define UART_CTRL_ADDR      8'h18
`define UART_STATUS_ADDR    8'h1C

`define SPI_CTRL_ADDR       8'h20
`define SPI_STATUS_ADDR     8'h24

`define I2C_CTRL_ADDR       8'h28
`define I2C_STATUS_ADDR     8'h2C

`define IRQ_ENABLE_ADDR     8'h30
`define IRQ_STATUS_ADDR     8'h34

`endif

examples/OPC/rtl/opc_parameters.vh
/******************************************************************************
* Project : Open Peripheral Controller (OPC)
* File    : opc_parameters.vh
* Author  : Dr. Lukram Dhanachandra Singh
*
* Description:
* Global design parameters used throughout the OPC project.
******************************************************************************/

`ifndef OPC_PARAMETERS_VH
`define OPC_PARAMETERS_VH

//==============================================================
// Global Parameters
//==============================================================

parameter DATA_WIDTH = 32;
parameter ADDR_WIDTH = 8;
parameter GPIO_WIDTH = 8;
parameter NUM_REGISTERS = 8;
//==============================================================
// Future Expansion
//==============================================================

parameter TIMER_WIDTH = 32;
parameter UART_DATA_WIDTH = 8;
parameter SPI_DATA_WIDTH = 8;
parameter I2C_DATA_WIDTH = 8;

`endif

examples/OPC/rtl/configuration_register_block.v
/**********************************************************************
* Project : Open Peripheral Controller (OPC)
* Module  : Configuration Register Block (CRB)
* File    : configuration_register_block.v
*
* Description:
* Generic memory-mapped register block used to configure OPC
* peripherals through a common register interface.
*
* Author  : Dr. Lukram Dhanachandra Singh
* Book    : Digital ASIC Design
*           The Complete RTL-to-GDSII Methodology
*           Using Open-Source EDA Tools
**********************************************************************/

`timescale 1ns / 1ps

`include "opc_parameters.vh"
`include "opc_defines.vh"

module configuration_register_block
(
    //------------------------------------------------------------------
    // Global Signals
    //------------------------------------------------------------------
    input  wire                      clk,
    input  wire                      rst_n,

    //------------------------------------------------------------------
    // Generic Register Interface
    //------------------------------------------------------------------
    input  wire                      write_en_i,
    input  wire                      read_en_i,

    input  wire [ADDR_WIDTH-1:0]     addr_i,
    input  wire [DATA_WIDTH-1:0]     wdata_i,

    output reg  [DATA_WIDTH-1:0]     rdata_o,

    //------------------------------------------------------------------
    // Peripheral Outputs
    //------------------------------------------------------------------
    output wire [GPIO_WIDTH-1:0]     gpio_data_o,
    output wire [GPIO_WIDTH-1:0]     gpio_dir_o
);

    //------------------------------------------------------------------
    // Internal Register File
    //------------------------------------------------------------------

    reg [DATA_WIDTH-1:0] reg_file [0:NUM_REGISTERS-1];

    integer i;

    //------------------------------------------------------------------
    // Register Index
    //------------------------------------------------------------------

    localparam REG_INDEX_WIDTH = $clog2(NUM_REGISTERS);
    //localparam [REG_INDEX_WIDTH-1:0] NUM_REGISTERS_MAX = NUM_REGISTERS;

    wire [REG_INDEX_WIDTH-1:0] reg_index;

    // Convert byte address to register index
    assign reg_index = addr_i[REG_INDEX_WIDTH+1:2];

    //------------------------------------------------------------------
    // Register Aliases
    //------------------------------------------------------------------

    //wire [DATA_WIDTH-1:0] gpio_data_reg;
    //wire [DATA_WIDTH-1:0] gpio_dir_reg;

    //assign gpio_data_reg = reg_file[`GPIO_DATA_REG];
    //assign gpio_dir_reg  = reg_file[`GPIO_DIR_REG];

    //------------------------------------------------------------------
    // Peripheral Output Mapping
    //------------------------------------------------------------------

    assign gpio_data_o = reg_file[`GPIO_DATA_REG][GPIO_WIDTH-1:0];
    assign gpio_dir_o  = reg_file[`GPIO_DIR_REG][GPIO_WIDTH-1:0];

    //------------------------------------------------------------------
    // Register Write Logic
    //------------------------------------------------------------------

    always @(posedge clk or negedge rst_n)
    begin
        if (!rst_n)
        begin
            for (i = 0; i < NUM_REGISTERS; i = i + 1)
                reg_file[i] <= {DATA_WIDTH{1'b0}};
        end
        else
        begin
            if (write_en_i)
	    begin
    		reg_file[reg_index] <= wdata_i;
	    end
        end
    end

    //------------------------------------------------------------------
    // Register Read Logic
    //------------------------------------------------------------------

    always @(*)
    begin
        rdata_o = {DATA_WIDTH{1'b0}};

        if (read_en_i)
	begin
    	    rdata_o = reg_file[reg_index];
	end
    end

`ifndef SYNTHESIS

    //------------------------------------------------------------------
    // Simulation Checks
    //------------------------------------------------------------------

    always @(*)
    begin
        if ((write_en_i || read_en_i) && (addr_i[1:0] != 2'b00))
            $display("WARNING: CRB - Unaligned register access at address %h", addr_i);
    end

`endif

endmodule

examples/OPC/tb/configuration_register_block_tb.v
/**********************************************************************
* Project : Open Peripheral Controller (OPC)
* Module  : Configuration Register Block Testbench
* File    : configuration_register_block_tb.v
*
* Description:
* Self-checking testbench for the Configuration Register Block.
*
* Author  : Dr. Lukram Dhanachandra Singh
* Book    : Digital ASIC Design
*           The Complete RTL-to-GDSII Methodology
*           Using Open-Source EDA Tools
**********************************************************************/

`timescale 1ns/1ps

`include "opc_parameters.vh"
`include "opc_defines.vh"

module configuration_register_block_tb;

    //------------------------------------------------------------
    // Clock & Reset
    //------------------------------------------------------------

    reg clk;
    reg rst_n;

    //------------------------------------------------------------
    // Generic Register Interface
    //------------------------------------------------------------

    reg                     write_en_i;
    reg                     read_en_i;

    reg  [ADDR_WIDTH-1:0]   addr_i;
    reg  [DATA_WIDTH-1:0]   wdata_i;

    wire [DATA_WIDTH-1:0]   rdata_o;

    //------------------------------------------------------------
    // Peripheral Outputs
    //------------------------------------------------------------

    wire [GPIO_WIDTH-1:0] gpio_data_o;
    wire [GPIO_WIDTH-1:0] gpio_dir_o;

    //------------------------------------------------------------
    // DUT
    //------------------------------------------------------------

    configuration_register_block dut
    (
        .clk(clk),
        .rst_n(rst_n),

        .write_en_i(write_en_i),
        .read_en_i(read_en_i),

        .addr_i(addr_i),
        .wdata_i(wdata_i),

        .rdata_o(rdata_o),

        .gpio_data_o(gpio_data_o),
        .gpio_dir_o(gpio_dir_o)
    );

    //------------------------------------------------------------
    // Clock Generation
    //------------------------------------------------------------

    initial
        clk = 0;

    always #5 clk = ~clk;

    //------------------------------------------------------------
    // Waveform
    //------------------------------------------------------------

    initial
    begin
        $dumpfile("configuration_register_block.vcd");
        $dumpvars(0, configuration_register_block_tb);
    end

    //------------------------------------------------------------
    // Reset Task
    //------------------------------------------------------------

    task reset_dut;
    begin

        rst_n       = 0;
        write_en_i  = 0;
        read_en_i   = 0;
        addr_i      = 0;
        wdata_i     = 0;

        repeat(2) @(posedge clk);

        rst_n = 1;

        @(posedge clk);

    end
    endtask

    //------------------------------------------------------------
    // Write Task
    //------------------------------------------------------------

    task write_register;

        input [ADDR_WIDTH-1:0] address;
        input [DATA_WIDTH-1:0] data;

    begin

        @(posedge clk);

        write_en_i = 1;
        addr_i     = address;
        wdata_i    = data;

        @(posedge clk);

        write_en_i = 0;
        addr_i     = 0;
        wdata_i    = 0;

    end
    endtask

    //------------------------------------------------------------
    // Read Task
    //------------------------------------------------------------

    task read_register;

        input [ADDR_WIDTH-1:0] address;

    begin

        @(posedge clk);

        read_en_i = 1;
        addr_i    = address;

        @(posedge clk);

        read_en_i = 0;
        addr_i    = 0;

    end
    endtask

    //------------------------------------------------------------
    // Test Sequence
    //------------------------------------------------------------

    initial
    begin

        $display("\n=========================================");
        $display(" OPC Configuration Register Block Test");
        $display("=========================================\n");

        //--------------------------------------------------------
        // Reset Test
        //--------------------------------------------------------

        reset_dut();

        if(gpio_data_o == 0 && gpio_dir_o == 0)
            $display("PASS : Reset Test");
        else
            $display("FAIL : Reset Test");

        //--------------------------------------------------------
        // GPIO DATA Register
        //--------------------------------------------------------

        write_register(`GPIO_DATA_ADDR, 32'h000000A5);

        if(gpio_data_o == 8'hA5)
            $display("PASS : GPIO_DATA Write");
        else
            $display("FAIL : GPIO_DATA Write");

        read_register(`GPIO_DATA_ADDR);

        if(rdata_o == 32'h000000A5)
            $display("PASS : GPIO_DATA Read");
        else
            $display("FAIL : GPIO_DATA Read");

        //--------------------------------------------------------
        // GPIO DIR Register
        //--------------------------------------------------------

        write_register(`GPIO_DIR_ADDR, 32'h000000FF);

        if(gpio_dir_o == 8'hFF)
            $display("PASS : GPIO_DIR Write");
        else
            $display("FAIL : GPIO_DIR Write");

        read_register(`GPIO_DIR_ADDR);

        if(rdata_o == 32'h000000FF)
            $display("PASS : GPIO_DIR Read");
        else
            $display("FAIL : GPIO_DIR Read");

        //--------------------------------------------------------
        // Multiple Register Test
        //--------------------------------------------------------

        write_register(`GPIO_DATA_ADDR,32'h55);
        write_register(`GPIO_DIR_ADDR ,32'hAA);

        if(gpio_data_o == 8'h55 &&
           gpio_dir_o  == 8'hAA)
            $display("PASS : Multiple Register Test");
        else
            $display("FAIL : Multiple Register Test");

        //--------------------------------------------------------
        // Invalid Address
        //--------------------------------------------------------

        read_register(8'h7C);

        if(rdata_o == 0)
            $display("PASS : Invalid Address Test");
        else
            $display("FAIL : Invalid Address Test");

        //--------------------------------------------------------
        // Finish
        //--------------------------------------------------------

        $display("\n=========================================");
        $display(" CRB Verification Completed");
        $display("=========================================\n");

        #20;

        $finish;

    end

endmodule

examples/OPC/configuration_register_block.vcd
$version Generated by VerilatedVcd $end
$timescale 1ps $end
 $scope module $unit $end
  $var wire 32 7 DATA_WIDTH [31:0] $end
  $var wire 32 8 ADDR_WIDTH [31:0] $end
  $var wire 32 8 GPIO_WIDTH [31:0] $end
  $var wire 32 8 NUM_REGISTERS [31:0] $end
  $var wire 32 7 TIMER_WIDTH [31:0] $end
  $var wire 32 8 UART_DATA_WIDTH [31:0] $end
  $var wire 32 8 SPI_DATA_WIDTH [31:0] $end
  $var wire 32 8 I2C_DATA_WIDTH [31:0] $end
 $upscope $end
 $scope module configuration_register_block_tb $end
  $var wire 1 4 clk $end
  $var wire 1 # rst_n $end
  $var wire 1 $ write_en_i $end
  $var wire 1 % read_en_i $end
  $var wire 8 & addr_i [7:0] $end
  $var wire 32 ' wdata_i [31:0] $end
  $var wire 32 5 rdata_o [31:0] $end
  $var wire 8 ) gpio_data_o [7:0] $end
  $var wire 8 * gpio_dir_o [7:0] $end
  $scope module dut $end
   $var wire 1 4 clk $end
   $var wire 1 # rst_n $end
   $var wire 1 $ write_en_i $end
   $var wire 1 % read_en_i $end
   $var wire 8 & addr_i [7:0] $end
   $var wire 32 ' wdata_i [31:0] $end
   $var wire 32 5 rdata_o [31:0] $end
   $var wire 8 ) gpio_data_o [7:0] $end
   $var wire 8 * gpio_dir_o [7:0] $end
   $var wire 32 + reg_file[0] [31:0] $end
   $var wire 32 , reg_file[1] [31:0] $end
   $var wire 32 - reg_file[2] [31:0] $end
   $var wire 32 . reg_file[3] [31:0] $end
   $var wire 32 / reg_file[4] [31:0] $end
   $var wire 32 0 reg_file[5] [31:0] $end
   $var wire 32 1 reg_file[6] [31:0] $end
   $var wire 32 2 reg_file[7] [31:0] $end
   $var wire 32 3 i [31:0] $end
   $var wire 32 6 REG_INDEX_WIDTH [31:0] $end
   $var wire 3 ( reg_index [2:0] $end
  $upscope $end
 $upscope $end
$enddefinitions $end


#0
0#
0$
0%
b00000000 &
b00000000000000000000000000000000 '
b000 (
b00000000 )
b00000000 *
b00000000000000000000000000000000 +
b00000000000000000000000000000000 ,
b00000000000000000000000000000000 -
b00000000000000000000000000000000 .
b00000000000000000000000000000000 /
b00000000000000000000000000000000 0
b00000000000000000000000000000000 1
b00000000000000000000000000000000 2
b00000000000000000000000000000000 3
04
b00000000000000000000000000000000 5
b00000000000000000000000000000011 6
b00000000000000000000000000100000 7
b00000000000000000000000000001000 8
#5000
b00000000000000000000000000001000 3
14
#10000
04
#15000
1#
14
#20000
04
#25000
14
#30000
04
#35000
1$
b00000000000000000000000010100101 '
b10100101 )
b00000000000000000000000010100101 +
14
#40000
04
#45000
0$
b00000000000000000000000000000000 '
14
#50000
04
#55000
1%
14
b00000000000000000000000010100101 5
#60000
04
#65000
0%
14
b00000000000000000000000000000000 5
#70000
04
#75000
1$
b00000100 &
b00000000000000000000000011111111 '
b001 (
b11111111 *
b00000000000000000000000011111111 ,
14
#80000
04
#85000
0$
b00000000 &
b00000000000000000000000000000000 '
b000 (
14
#90000
04
#95000
1%
b00000100 &
b001 (
14
b00000000000000000000000011111111 5
#100000
04
#105000
0%
b00000000 &
b000 (
14
b00000000000000000000000000000000 5
#110000
04
#115000
1$
b00000000000000000000000001010101 '
b01010101 )
b00000000000000000000000001010101 +
14
#120000
04
#125000
0$
b00000000000000000000000000000000 '
14
#130000
04
#135000
1$
b00000100 &
b00000000000000000000000010101010 '
b001 (
b10101010 *
b00000000000000000000000010101010 ,
14
#140000
04
#145000
0$
b00000000 &
b00000000000000000000000000000000 '
b000 (
14
#150000
04
#155000
1%
b01111100 &
b111 (
14
#160000
04
#165000
0%
b00000000 &
b000 (
14
