examples/OPC/rtl/opc_parameters.vh
/******************************************************************************
* Project : Open Peripheral Controller (OPC)
* File    : opc_parameters.vh
* Author  : Dr. Lukram Dhanachandra Singh
*
* Description:
* Global design parameters used throughout the OPC project.
******************************************************************************/

`ifndef OPC_PARAMETERS_VH
`define OPC_PARAMETERS_VH

//==============================================================
// Global Parameters
//==============================================================

parameter DATA_WIDTH = 32;
parameter ADDR_WIDTH = 8;
parameter GPIO_WIDTH = 8;
parameter NUM_REGISTERS = 8;

//----------------------------------------------------------------------
// APB Parameters
//----------------------------------------------------------------------

parameter APB_ADDR_WIDTH = 32;
parameter REG_ADDR_LSB   = 2;


//==============================================================
// Future Expansion
//==============================================================

parameter TIMER_WIDTH = 32;
parameter UART_DATA_WIDTH = 8;
parameter SPI_DATA_WIDTH = 8;
parameter I2C_DATA_WIDTH = 8;

`endif

examples/OPC/rtl/gpio_controller.v
/******************************************************************************
* Project : Open Peripheral Controller (OPC)
* Module  : GPIO Controller
* File    : gpio_controller.v
*
* Description:
* Parameterizable GPIO Controller for the Open Peripheral Controller (OPC).
* The module controls GPIO output pins and samples GPIO input pins based on
* the direction configuration received from the Configuration Register Block.
*
* Features:
* - Parameterizable GPIO width
* - Active-low asynchronous reset
* - Synchronous operation
* - Technology-independent RTL
* - Fully synthesizable
*
* Author  : Dr. Lukram Dhanachandra Singh
* Book    : Digital ASIC Design:
*           The Complete RTL-to-GDSII Methodology
*           Using Open-Source EDA Tools
******************************************************************************/

`timescale 1ns/1ps

`include "opc_parameters.vh"

module gpio_controller
(
    //----------------------------------------------------------------------
    // Global Signals
    //----------------------------------------------------------------------

    input  wire                     clk,
    input  wire                     rst_n,

    //----------------------------------------------------------------------
    // Control Interface
    //----------------------------------------------------------------------

    input  wire [GPIO_WIDTH-1:0]    gpio_data_i,
    input  wire [GPIO_WIDTH-1:0]    gpio_dir_i,

    //----------------------------------------------------------------------
    // GPIO Interface
    //----------------------------------------------------------------------

    input  wire [GPIO_WIDTH-1:0]    gpio_in_i,

    output reg  [GPIO_WIDTH-1:0]    gpio_out_o,
    output reg  [GPIO_WIDTH-1:0]    gpio_input_o

);

    //----------------------------------------------------------------------
    // Internal Signals
    //----------------------------------------------------------------------


// Sequential logic
integer i;

always @(posedge clk or negedge rst_n) begin
    if (!rst_n) begin
        gpio_out_o   <= {GPIO_WIDTH{1'b0}};
        gpio_input_o <= {GPIO_WIDTH{1'b0}};
    end
    else begin

        // Sample all GPIO inputs every clock cycle
        gpio_input_o <= gpio_in_i;

        // Drive GPIO outputs based on direction
        for (i = 0; i < GPIO_WIDTH; i = i + 1) begin
            if (gpio_dir_i[i])
                gpio_out_o[i] <= gpio_data_i[i];
            else
                gpio_out_o[i] <= 1'b0;
        end

    end
end

endmodule

examples/OPC/tb/gpio_controller_tb.v
/******************************************************************************
* Project : Open Peripheral Controller (OPC)
* Module  : GPIO Controller Testbench
* File    : gpio_controller_tb.v
*
* Description:
* Testbench for verifying the functionality of the GPIO Controller.
*
* Verification Scenarios:
* 1. Reset Verification
* 2. GPIO Output Mode
* 3. GPIO Input Mode
* 4. Mixed Input/Output Operation
*
* Author  : Dr. Lukram Dhanachandra Singh
* Book    : Digital ASIC Design:
*           The Complete RTL-to-GDSII Methodology
*           Using Open-Source EDA Tools
******************************************************************************/

`timescale 1ns/1ps
`include "opc_parameters.vh"
module gpio_controller_tb;

    //----------------------------------------------------------------------
    // Parameters
    //----------------------------------------------------------------------


    //----------------------------------------------------------------------
    // Testbench Signals
    //----------------------------------------------------------------------

    reg                       clk;
    reg                       rst_n;

    reg  [GPIO_WIDTH-1:0]     gpio_data_i;
    reg  [GPIO_WIDTH-1:0]     gpio_dir_i;
    reg  [GPIO_WIDTH-1:0]     gpio_in_i;

    wire [GPIO_WIDTH-1:0]     gpio_out_o;
    wire [GPIO_WIDTH-1:0]     gpio_input_o;

    //----------------------------------------------------------------------
    // Instantiate GPIO Controller
    //----------------------------------------------------------------------

    gpio_controller uut (
        .clk          (clk),
        .rst_n        (rst_n),
        .gpio_data_i  (gpio_data_i),
        .gpio_dir_i   (gpio_dir_i),
        .gpio_in_i    (gpio_in_i),
        .gpio_out_o   (gpio_out_o),
        .gpio_input_o (gpio_input_o)
    );

    //----------------------------------------------------------------------
    // Clock Generation
    //----------------------------------------------------------------------

    initial begin
        clk = 1'b0;
        forever #5 clk = ~clk;
    end

    //----------------------------------------------------------------------
    // Test Sequence
    //----------------------------------------------------------------------

    initial begin
	$dumpfile("gpio_controller.vcd");
    	$dumpvars(0, gpio_controller_tb);

        $display("==============================================");
        $display(" GPIO Controller Testbench");
        $display("==============================================");

        //--------------------------------------------------------------
        // Initialize Inputs
        //--------------------------------------------------------------

        rst_n       = 1'b0;
        gpio_data_i = 8'h00;
        gpio_dir_i  = 8'h00;
        gpio_in_i   = 8'h00;

        //--------------------------------------------------------------
        // Apply Reset
        //--------------------------------------------------------------

        #20;
        rst_n = 1'b1;

	#10;

	if ((gpio_out_o == 8'h00) &&
    	(gpio_input_o == 8'h00))
	    $display("PASS : Reset");
	else
	    $display("FAIL : Reset");

        //--------------------------------------------------------------
        // Test Case 1
        // Configure all GPIOs as outputs
        //--------------------------------------------------------------

        $display("Test Case 1 : Output Mode");

        gpio_dir_i  = 8'hFF;
        gpio_data_i = 8'hA5;

        #20;
	
	if (gpio_out_o == 8'hA5)
	    $display("PASS : Output Mode");
	else
	    $display("FAIL : Output Mode");

        //--------------------------------------------------------------
        // Test Case 2
        // Configure all GPIOs as inputs
        //--------------------------------------------------------------

        $display("Test Case 2 : Input Mode");

        gpio_dir_i = 8'h00;
        gpio_in_i  = 8'h3C;

        #20;
	if (gpio_input_o == 8'h3C)
    		$display("PASS : Input Mode");
	else
    		$display("FAIL : Input Mode");

        //--------------------------------------------------------------
        // Test Case 3
        // Mixed Direction
        //--------------------------------------------------------------

        $display("Test Case 3 : Mixed Mode");

        gpio_dir_i  = 8'b11110000;
        gpio_data_i = 8'b10100000;
        gpio_in_i   = 8'b00001111;

        #20;

	if ((gpio_out_o == 8'hA0) &&
	    (gpio_input_o == 8'h0F))
	    $display("PASS : Mixed Mode");
	else
	    $display("FAIL : Mixed Mode");	

        //--------------------------------------------------------------
        // End Simulation
        //--------------------------------------------------------------

        $display("==============================================");
	$display(" GPIO Controller Verification Completed");
	$display("==============================================");
        $finish;

    end

    //----------------------------------------------------------------------
    // Monitor Signals
    //----------------------------------------------------------------------

    initial begin

        $monitor("Time=%0t | rst_n=%b | dir=%b | data=%b | gpio_in=%b | gpio_out=%b | sampled=%b",
                  $time,
                  rst_n,
                  gpio_dir_i,
                  gpio_data_i,
                  gpio_in_i,
                  gpio_out_o,
                  gpio_input_o);

    end

endmodule

examples/OPC/gpio_controller.vcd
$version Generated by VerilatedVcd $end
$timescale 1ps $end
 $scope module $unit $end
  $var wire 32 + DATA_WIDTH [31:0] $end
  $var wire 32 , ADDR_WIDTH [31:0] $end
  $var wire 32 , GPIO_WIDTH [31:0] $end
  $var wire 32 + TIMER_WIDTH [31:0] $end
  $var wire 32 , UART_DATA_WIDTH [31:0] $end
  $var wire 32 , SPI_DATA_WIDTH [31:0] $end
  $var wire 32 , I2C_DATA_WIDTH [31:0] $end
 $upscope $end
 $scope module gpio_controller_tb $end
  $var wire 1 & clk $end
  $var wire 1 ' rst_n $end
  $var wire 8 ( gpio_data_i [7:0] $end
  $var wire 8 ) gpio_dir_i [7:0] $end
  $var wire 8 * gpio_in_i [7:0] $end
  $var wire 8 # gpio_out_o [7:0] $end
  $var wire 8 $ gpio_input_o [7:0] $end
  $scope module uut $end
   $var wire 1 & clk $end
   $var wire 1 ' rst_n $end
   $var wire 8 ( gpio_data_i [7:0] $end
   $var wire 8 ) gpio_dir_i [7:0] $end
   $var wire 8 * gpio_in_i [7:0] $end
   $var wire 8 # gpio_out_o [7:0] $end
   $var wire 8 $ gpio_input_o [7:0] $end
   $var wire 32 % i [31:0] $end
  $upscope $end
 $upscope $end
$enddefinitions $end


#0
b00000000 #
b00000000 $
b00000000000000000000000000000000 %
0&
0'
b00000000 (
b00000000 )
b00000000 *
b00000000000000000000000000100000 +
b00000000000000000000000000001000 ,
#5000
1&
#10000
0&
#15000
1&
#20000
0&
1'
#25000
b00000000000000000000000000001000 %
1&
#30000
0&
b10100101 (
b11111111 )
#35000
b10100101 #
1&
#40000
0&
#45000
1&
#50000
0&
b00000000 )
b00111100 *
#55000
b00000000 #
b00111100 $
1&
#60000
0&
#65000
1&
#70000
0&
b10100000 (
b11110000 )
b00001111 *
#75000
b10100000 #
b00001111 $
1&
