examples/OPC/rtl/opc_defines.vh
/******************************************************************************
* Project : Open Peripheral Controller (OPC)
* File    : opc_defines.vh
*
* Description:
* Register address definitions.
******************************************************************************/

`ifndef OPC_DEFINES_VH
`define OPC_DEFINES_VH

//==============================================================
// GPIO Register Addresses
//==============================================================

`define GPIO_DATA_ADDR      8'h00
`define GPIO_DIR_ADDR       8'h04
`define GPIO_IN_ADDR        8'h08
`define GPIO_OUT_ADDR       8'h0C

/**********************************************************************
* Register File Indices
**********************************************************************/

`define GPIO_DATA_REG      0
`define GPIO_DIR_REG       1

`define TIMER_CTRL_REG     2
`define TIMER_VALUE_REG    3

`define UART_CTRL_REG      4
`define UART_STATUS_REG    5

`define SPI_CTRL_REG       6
`define SPI_STATUS_REG     7

//==============================================================
// Future Peripheral Registers
//==============================================================

`define TIMER_CTRL_ADDR     8'h10
`define TIMER_COUNT_ADDR    8'h14

`define UART_CTRL_ADDR      8'h18
`define UART_STATUS_ADDR    8'h1C

`define SPI_CTRL_ADDR       8'h20
`define SPI_STATUS_ADDR     8'h24

`define I2C_CTRL_ADDR       8'h28
`define I2C_STATUS_ADDR     8'h2C

`define IRQ_ENABLE_ADDR     8'h30
`define IRQ_STATUS_ADDR     8'h34

`endif

examples/OPC/rtl/opc_parameters.vh
/******************************************************************************
* Project : Open Peripheral Controller (OPC)
* File    : opc_parameters.vh
* Author  : Dr. Lukram Dhanachandra Singh
*
* Description:
* Global design parameters used throughout the OPC project.
******************************************************************************/

`ifndef OPC_PARAMETERS_VH
`define OPC_PARAMETERS_VH

//==============================================================
// Global Parameters
//==============================================================

parameter DATA_WIDTH = 32;
parameter ADDR_WIDTH = 8;
parameter GPIO_WIDTH = 8;
parameter NUM_REGISTERS = 8;

//----------------------------------------------------------------------
// APB Parameters
//----------------------------------------------------------------------

parameter APB_ADDR_WIDTH = 32;
parameter REG_ADDR_LSB   = 2;


//==============================================================
// Future Expansion
//==============================================================

parameter TIMER_WIDTH = 32;
parameter UART_DATA_WIDTH = 8;
parameter SPI_DATA_WIDTH = 8;
parameter I2C_DATA_WIDTH = 8;

`endif

examples/OPC/rtl/gpio_controller.v
/******************************************************************************
* Project : Open Peripheral Controller (OPC)
* Module  : GPIO Controller
* File    : gpio_controller.v
*
* Description:
* Parameterizable GPIO Controller for the Open Peripheral Controller (OPC).
* The module controls GPIO output pins and samples GPIO input pins based on
* the direction configuration received from the Configuration Register Block.
*
* Features:
* - Parameterizable GPIO width
* - Active-low asynchronous reset
* - Synchronous operation
* - Technology-independent RTL
* - Fully synthesizable
*
* Author  : Dr. Lukram Dhanachandra Singh
* Book    : Digital ASIC Design:
*           The Complete RTL-to-GDSII Methodology
*           Using Open-Source EDA Tools
******************************************************************************/

`timescale 1ns/1ps

`include "opc_parameters.vh"

module gpio_controller
(
    //----------------------------------------------------------------------
    // Global Signals
    //----------------------------------------------------------------------

    input  wire                     clk,
    input  wire                     rst_n,

    //----------------------------------------------------------------------
    // Control Interface
    //----------------------------------------------------------------------

    input  wire [GPIO_WIDTH-1:0]    gpio_data_i,
    input  wire [GPIO_WIDTH-1:0]    gpio_dir_i,

    //----------------------------------------------------------------------
    // GPIO Interface
    //----------------------------------------------------------------------

    input  wire [GPIO_WIDTH-1:0]    gpio_in_i,

    output reg  [GPIO_WIDTH-1:0]    gpio_out_o,
    output reg  [GPIO_WIDTH-1:0]    gpio_input_o

);

    //----------------------------------------------------------------------
    // Internal Signals
    //----------------------------------------------------------------------


// Sequential logic
integer i;

always @(posedge clk or negedge rst_n) begin
    if (!rst_n) begin
        gpio_out_o   <= {GPIO_WIDTH{1'b0}};
        gpio_input_o <= {GPIO_WIDTH{1'b0}};
    end
    else begin

        // Sample all GPIO inputs every clock cycle
        gpio_input_o <= gpio_in_i;

        // Drive GPIO outputs based on direction
        for (i = 0; i < GPIO_WIDTH; i = i + 1) begin
            if (gpio_dir_i[i])
                gpio_out_o[i] <= gpio_data_i[i];
            else
                gpio_out_o[i] <= 1'b0;
        end

    end
end

endmodule

examples/OPC/rtl/configuration_register_block.v
/**********************************************************************
* Project : Open Peripheral Controller (OPC)
* Module  : Configuration Register Block (CRB)
* File    : configuration_register_block.v
*
* Description:
* Generic memory-mapped register block used to configure OPC
* peripherals through a common register interface.
*
* Author  : Dr. Lukram Dhanachandra Singh
* Book    : Digital ASIC Design
*           The Complete RTL-to-GDSII Methodology
*           Using Open-Source EDA Tools
**********************************************************************/

`timescale 1ns / 1ps

`include "opc_parameters.vh"
`include "opc_defines.vh"

module configuration_register_block
(
    //------------------------------------------------------------------
    // Global Signals
    //------------------------------------------------------------------
    input  wire                      clk,
    input  wire                      rst_n,

    //------------------------------------------------------------------
    // Generic Register Interface
    //------------------------------------------------------------------
    input  wire                      write_en_i,
    input  wire                      read_en_i,

    input  wire [ADDR_WIDTH-1:0]     addr_i,
    input  wire [DATA_WIDTH-1:0]     wdata_i,

    output reg  [DATA_WIDTH-1:0]     rdata_o,

    //------------------------------------------------------------------
    // Peripheral Outputs
    //------------------------------------------------------------------
    output wire [GPIO_WIDTH-1:0]     gpio_data_o,
    output wire [GPIO_WIDTH-1:0]     gpio_dir_o
);

    //------------------------------------------------------------------
    // Internal Register File
    //------------------------------------------------------------------

    reg [DATA_WIDTH-1:0] reg_file [0:NUM_REGISTERS-1];

    integer i;

    //------------------------------------------------------------------
    // Register Index
    //------------------------------------------------------------------

    localparam REG_INDEX_WIDTH = $clog2(NUM_REGISTERS);
    //localparam [REG_INDEX_WIDTH-1:0] NUM_REGISTERS_MAX = NUM_REGISTERS;

    wire [REG_INDEX_WIDTH-1:0] reg_index;

    // Convert byte address to register index
    assign reg_index = addr_i[REG_INDEX_WIDTH+1:2];
    //assign reg_index = addr_i[REG_INDEX_WIDTH-1:0];

    //------------------------------------------------------------------
    // Register Aliases
    //------------------------------------------------------------------

    //wire [DATA_WIDTH-1:0] gpio_data_reg;
    //wire [DATA_WIDTH-1:0] gpio_dir_reg;

    //assign gpio_data_reg = reg_file[`GPIO_DATA_REG];
    //assign gpio_dir_reg  = reg_file[`GPIO_DIR_REG];

    //------------------------------------------------------------------
    // Peripheral Output Mapping
    //------------------------------------------------------------------

    assign gpio_data_o = reg_file[`GPIO_DATA_REG][GPIO_WIDTH-1:0];
    assign gpio_dir_o  = reg_file[`GPIO_DIR_REG][GPIO_WIDTH-1:0];

    //------------------------------------------------------------------
    // Register Write Logic
    //------------------------------------------------------------------

    always @(posedge clk or negedge rst_n)
    begin
        if (!rst_n)
        begin
            for (i = 0; i < NUM_REGISTERS; i = i + 1)
                reg_file[i] <= {DATA_WIDTH{1'b0}};
        end
        else
        begin
            if (write_en_i)
	    begin
    		reg_file[reg_index] <= wdata_i;
	    end
        end
    end

    //------------------------------------------------------------------
    // Register Read Logic
    //------------------------------------------------------------------

    always @(*)
    begin
        rdata_o = {DATA_WIDTH{1'b0}};

        if (read_en_i)
	begin
    	    rdata_o = reg_file[reg_index];
	end
    end

`ifndef SYNTHESIS

    //------------------------------------------------------------------
    // Simulation Checks
    //------------------------------------------------------------------

    always @(*)
    begin
        if ((write_en_i || read_en_i) && (addr_i[1:0] != 2'b00))
	//if ((write_en_i || read_en_i) && (addr_i >= NUM_REGISTERS))
            $display("WARNING: CRB - Unaligned register access at address %h", addr_i);
    end

`endif

endmodule

examples/OPC/rtl/opc_top.v
/**********************************************************************
* Project : Open Peripheral Controller (OPC)
* Module  : OPC Top
* File    : opc_top.v
*
* Description:
* Top-level integration module for the Open Peripheral Controller.
* This module connects the Configuration Register Block (CRB)
* with the GPIO Controller through the generic register interface.
*
* Author  : Dr. Lukram Dhanachandra Singh
* Book    : Digital ASIC Design
*           The Complete RTL-to-GDSII Methodology
*           Using Open-Source EDA Tools
**********************************************************************/

`timescale 1ns/1ps

`include "opc_parameters.vh"
`include "opc_defines.vh"

module opc_top
(
    //------------------------------------------------------------------
    // Global Signals
    //------------------------------------------------------------------
    input  wire                     clk,
    input  wire                     rst_n,

    //------------------------------------------------------------------
    // Generic Register Interface
    //------------------------------------------------------------------
    input  wire                     write_en_i,
    input  wire                     read_en_i,

    input  wire [ADDR_WIDTH-1:0]    addr_i,
    input  wire [DATA_WIDTH-1:0]    wdata_i,

    output wire [DATA_WIDTH-1:0]    rdata_o,

    //------------------------------------------------------------------
    // External GPIO
    //------------------------------------------------------------------
    input  wire [GPIO_WIDTH-1:0]    gpio_in_i,

    output wire [GPIO_WIDTH-1:0]    gpio_out_o,
    output wire [GPIO_WIDTH-1:0]    gpio_input_o
);

    //------------------------------------------------------------------
    // Internal Signals
    //------------------------------------------------------------------

    wire [GPIO_WIDTH-1:0] gpio_data;
    wire [GPIO_WIDTH-1:0] gpio_dir;

    //------------------------------------------------------------------
    // Configuration Register Block
    //------------------------------------------------------------------

    configuration_register_block u_crb
    (
        .clk(clk),
        .rst_n(rst_n),

        .write_en_i(write_en_i),
        .read_en_i(read_en_i),

        .addr_i(addr_i),
        .wdata_i(wdata_i),

        .rdata_o(rdata_o),

        .gpio_data_o(gpio_data),
        .gpio_dir_o(gpio_dir)
    );

    //------------------------------------------------------------------
    // GPIO Controller
    //------------------------------------------------------------------

    gpio_controller u_gpio
    (
        .clk(clk),
        .rst_n(rst_n),

        .gpio_data_i(gpio_data),
        .gpio_dir_i(gpio_dir),

        .gpio_in_i(gpio_in_i),

        .gpio_out_o(gpio_out_o),
        .gpio_input_o(gpio_input_o)
    );

endmodule

examples/OPC/tb/opc_top_tb.v
/**********************************************************************
* Project : Open Peripheral Controller (OPC)
* Module  : OPC Top Testbench
* File    : opc_top_tb.v
*
* Description:
* Self-checking testbench for the OPC Top module.
*
* Author  : Dr. Lukram Dhanachandra Singh
* Book    : Digital ASIC Design
*           The Complete RTL-to-GDSII Methodology
*           Using Open-Source EDA Tools
**********************************************************************/

`timescale 1ns/1ps

`include "opc_parameters.vh"
`include "opc_defines.vh"

module opc_top_tb;

    //------------------------------------------------------------
    // Global Signals
    //------------------------------------------------------------

    reg clk;
    reg rst_n;

    //------------------------------------------------------------
    // Generic Register Interface
    //------------------------------------------------------------

    reg                     write_en_i;
    reg                     read_en_i;
    reg  [ADDR_WIDTH-1:0]   addr_i;
    reg  [DATA_WIDTH-1:0]   wdata_i;

    wire [DATA_WIDTH-1:0]   rdata_o;

    //------------------------------------------------------------
    // GPIO Signals
    //------------------------------------------------------------

    reg  [GPIO_WIDTH-1:0]   gpio_in_i;

    wire [GPIO_WIDTH-1:0]   gpio_out_o;
    wire [GPIO_WIDTH-1:0]   gpio_input_o;

    //------------------------------------------------------------
    // DUT
    //------------------------------------------------------------

    opc_top dut
    (
        .clk(clk),
        .rst_n(rst_n),

        .write_en_i(write_en_i),
        .read_en_i(read_en_i),

        .addr_i(addr_i),
        .wdata_i(wdata_i),

        .rdata_o(rdata_o),

        .gpio_in_i(gpio_in_i),

        .gpio_out_o(gpio_out_o),
        .gpio_input_o(gpio_input_o)
    );

    //------------------------------------------------------------
    // Clock Generation
    //------------------------------------------------------------

    initial
        clk = 1'b0;

    always #5 clk = ~clk;

    //------------------------------------------------------------
    // Waveform Dump
    //------------------------------------------------------------

    initial
    begin
        $dumpfile("opc_top.vcd");
        $dumpvars(0, opc_top_tb);
    end

    //------------------------------------------------------------
    // Reset Task
    //------------------------------------------------------------

    task reset_dut;
    begin

        rst_n      = 0;

        write_en_i = 0;
        read_en_i  = 0;

        addr_i     = 0;
        wdata_i    = 0;

        gpio_in_i  = 0;

        repeat(2) @(posedge clk);

        rst_n = 1;

        @(posedge clk);

    end
    endtask

    //------------------------------------------------------------
    // Register Write
    //------------------------------------------------------------

    task write_register;

        input [ADDR_WIDTH-1:0] address;
        input [DATA_WIDTH-1:0] data;

    begin

        @(posedge clk);

        write_en_i = 1;
        addr_i     = address;
        wdata_i    = data;

        @(posedge clk);

        write_en_i = 0;
        addr_i     = 0;
        wdata_i    = 0;

    end
    endtask

    //------------------------------------------------------------
    // Register Read
    //------------------------------------------------------------

    task read_register;

        input [ADDR_WIDTH-1:0] address;

    begin

        @(posedge clk);

        read_en_i = 1;
        addr_i    = address;

        @(posedge clk);

        read_en_i = 0;
        addr_i    = 0;

    end
    endtask

    //------------------------------------------------------------
    // Test Sequence
    //------------------------------------------------------------

    initial
    begin

        $display("");
        $display("==========================================");
        $display("      OPC TOP Integration Test");
        $display("==========================================");

        //--------------------------------------------------------
        // Reset
        //--------------------------------------------------------

        reset_dut();

        if(gpio_out_o == 8'h00)
            $display("PASS : Reset");
        else
            $display("FAIL : Reset");

        //--------------------------------------------------------
        // Configure GPIO as Output
        //--------------------------------------------------------

        write_register(`GPIO_DIR_ADDR,32'h000000FF);

        if(gpio_out_o == 8'h00)
            $display("PASS : GPIO Direction");
        else
            $display("FAIL : GPIO Direction");

        //--------------------------------------------------------
        // Write GPIO Data
        //--------------------------------------------------------

        write_register(`GPIO_DATA_ADDR,32'h000000A5);

	// Wait one clock cycle for propagation
	@(posedge clk);

	if(gpio_out_o == 8'hA5)
	    $display("PASS : GPIO Output");
	else begin
	    $display("FAIL : GPIO Output");
	    $display("Expected = A5");
	    $display("Actual   = %h", gpio_out_o);
	end

        //--------------------------------------------------------
        // Read GPIO Data Register
        //--------------------------------------------------------

        read_register(`GPIO_DATA_ADDR);

        if(rdata_o == 32'h000000A5)
            $display("PASS : Register Read");
        else
            $display("FAIL : Register Read");

        //--------------------------------------------------------
        // GPIO Input Test
        //--------------------------------------------------------

        gpio_in_i = 8'h3C;

        @(posedge clk);

        if(gpio_input_o == 8'h3C)
            $display("PASS : GPIO Input");
        else
            $display("FAIL : GPIO Input");

        //--------------------------------------------------------
        // Mixed Direction Test
        //--------------------------------------------------------

        write_register(`GPIO_DIR_ADDR,32'h000000F0);
        write_register(`GPIO_DATA_ADDR,32'h000000AA);

        if(gpio_out_o == 8'hA0)
            $display("PASS : Mixed Direction");
        else
            $display("FAIL : Mixed Direction");

        //--------------------------------------------------------
        // End of Simulation
        //--------------------------------------------------------

        $display("");
        $display("==========================================");
        $display(" OPC TOP Integration Completed");
        $display("==========================================");

        #20;

        $finish;

    end

endmodule

examples/OPC/opc_top.vcd
$version Generated by VerilatedVcd $end
$timescale 1ps $end
 $scope module $unit $end
  $var wire 32 ; DATA_WIDTH [31:0] $end
  $var wire 32 < ADDR_WIDTH [31:0] $end
  $var wire 32 < GPIO_WIDTH [31:0] $end
  $var wire 32 < NUM_REGISTERS [31:0] $end
  $var wire 32 ; TIMER_WIDTH [31:0] $end
  $var wire 32 < UART_DATA_WIDTH [31:0] $end
  $var wire 32 < SPI_DATA_WIDTH [31:0] $end
  $var wire 32 < I2C_DATA_WIDTH [31:0] $end
 $upscope $end
 $scope module opc_top_tb $end
  $var wire 1 8 clk $end
  $var wire 1 # rst_n $end
  $var wire 1 $ write_en_i $end
  $var wire 1 % read_en_i $end
  $var wire 8 & addr_i [7:0] $end
  $var wire 32 ' wdata_i [31:0] $end
  $var wire 32 9 rdata_o [31:0] $end
  $var wire 8 ( gpio_in_i [7:0] $end
  $var wire 8 * gpio_out_o [7:0] $end
  $var wire 8 + gpio_input_o [7:0] $end
  $scope module dut $end
   $var wire 1 8 clk $end
   $var wire 1 # rst_n $end
   $var wire 1 $ write_en_i $end
   $var wire 1 % read_en_i $end
   $var wire 8 & addr_i [7:0] $end
   $var wire 32 ' wdata_i [31:0] $end
   $var wire 32 9 rdata_o [31:0] $end
   $var wire 8 ( gpio_in_i [7:0] $end
   $var wire 8 * gpio_out_o [7:0] $end
   $var wire 8 + gpio_input_o [7:0] $end
   $var wire 8 , gpio_data [7:0] $end
   $var wire 8 - gpio_dir [7:0] $end
   $scope module u_crb $end
    $var wire 1 8 clk $end
    $var wire 1 # rst_n $end
    $var wire 1 $ write_en_i $end
    $var wire 1 % read_en_i $end
    $var wire 8 & addr_i [7:0] $end
    $var wire 32 ' wdata_i [31:0] $end
    $var wire 32 9 rdata_o [31:0] $end
    $var wire 8 , gpio_data_o [7:0] $end
    $var wire 8 - gpio_dir_o [7:0] $end
    $var wire 32 . reg_file[0] [31:0] $end
    $var wire 32 / reg_file[1] [31:0] $end
    $var wire 32 0 reg_file[2] [31:0] $end
    $var wire 32 1 reg_file[3] [31:0] $end
    $var wire 32 2 reg_file[4] [31:0] $end
    $var wire 32 3 reg_file[5] [31:0] $end
    $var wire 32 4 reg_file[6] [31:0] $end
    $var wire 32 5 reg_file[7] [31:0] $end
    $var wire 32 6 i [31:0] $end
    $var wire 32 : REG_INDEX_WIDTH [31:0] $end
    $var wire 3 ) reg_index [2:0] $end
   $upscope $end
   $scope module u_gpio $end
    $var wire 1 8 clk $end
    $var wire 1 # rst_n $end
    $var wire 8 , gpio_data_i [7:0] $end
    $var wire 8 - gpio_dir_i [7:0] $end
    $var wire 8 ( gpio_in_i [7:0] $end
    $var wire 8 * gpio_out_o [7:0] $end
    $var wire 8 + gpio_input_o [7:0] $end
    $var wire 32 7 i [31:0] $end
   $upscope $end
  $upscope $end
 $upscope $end
$enddefinitions $end


#0
0#
0$
0%
b00000000 &
b00000000000000000000000000000000 '
b00000000 (
b000 )
b00000000 *
b00000000 +
b00000000 ,
b00000000 -
b00000000000000000000000000000000 .
b00000000000000000000000000000000 /
b00000000000000000000000000000000 0
b00000000000000000000000000000000 1
b00000000000000000000000000000000 2
b00000000000000000000000000000000 3
b00000000000000000000000000000000 4
b00000000000000000000000000000000 5
b00000000000000000000000000000000 6
b00000000000000000000000000000000 7
08
b00000000000000000000000000000000 9
b00000000000000000000000000000011 :
b00000000000000000000000000100000 ;
b00000000000000000000000000001000 <
#5000
b00000000000000000000000000001000 6
18
#10000
08
#15000
1#
b00000000000000000000000000001000 7
18
#20000
08
#25000
18
#30000
08
#35000
1$
b00000100 &
b00000000000000000000000011111111 '
b001 )
b11111111 -
b00000000000000000000000011111111 /
18
#40000
08
#45000
0$
b00000000 &
b00000000000000000000000000000000 '
b000 )
18
#50000
08
#55000
1$
b00000000000000000000000010100101 '
b10100101 ,
b00000000000000000000000010100101 .
18
#60000
08
#65000
0$
b00000000000000000000000000000000 '
b10100101 *
18
#70000
08
#75000
18
#80000
08
#85000
1%
18
b00000000000000000000000010100101 9
#90000
08
#95000
0%
b00111100 (
b00111100 +
18
b00000000000000000000000000000000 9
#100000
08
#105000
18
#110000
08
#115000
1$
b00000100 &
b00000000000000000000000011110000 '
b001 )
b11110000 -
b00000000000000000000000011110000 /
18
#120000
08
#125000
0$
b00000000 &
b00000000000000000000000000000000 '
b000 )
b10100000 *
18
#130000
08
#135000
1$
b00000000000000000000000010101010 '
b10101010 ,
b00000000000000000000000010101010 .
18
#140000
08
#145000
0$
b00000000000000000000000000000000 '
18
